README.md
creds3.py
setup.cfg
setup.py
creds3.egg-info/PKG-INFO
creds3.egg-info/SOURCES.txt
creds3.egg-info/dependency_links.txt
creds3.egg-info/entry_points.txt
creds3.egg-info/requires.txt
creds3.egg-info/top_level.txt