Metadata-Version: 1.1
Name: creds3
Version: 1.0.3
Summary: A clone of Credstash for managing secrets in the cloud using AWS KMS and S3
Home-page: https://github.com/romanrev/creds3
Author: UNKNOWN
Author-email: UNKNOWN
License: Apache2
Platform: UNKNOWN
Classifier: Intended Audience :: Developers
Classifier: Intended Audience :: System Administrators
Classifier: License :: OSI Approved :: Apache Software License
